{
    "variants": {
        "ctop=false,cbottom=false,cnorth=false,csouth=false,ceast=false,cwest=false": { "model": "unimod:block/unicable_disconnected" },

        "ctop=true,cbottom=false,cnorth=false,csouth=false,ceast=false,cwest=false": { "model": "unimod:block/unicable_connected_transfer_1" },
        "ctop=false,cbottom=true,cnorth=false,csouth=false,ceast=false,cwest=false": { "model": "unimod:block/unicable_connected_transfer_1" },
        "ctop=false,cbottom=false,cnorth=true,csouth=false,ceast=false,cwest=false": { "model": "unimod:block/unicable_connected_transfer_1" },
        "ctop=false,cbottom=false,cnorth=false,csouth=true,ceast=false,cwest=false": { "model": "unimod:block/unicable_connected_transfer_1" },
        "ctop=false,cbottom=false,cnorth=false,csouth=false,ceast=true,cwest=false": { "model": "unimod:block/unicable_connected_transfer_1" },
        "ctop=false,cbottom=false,cnorth=false,csouth=false,ceast=false,cwest=true": { "model": "unimod:block/unicable_connected_transfer_1" },

        "ctop=true,cbottom=true,cnorth=false,csouth=false,ceast=false,cwest=false": { "model": "unimod:block/unicable_connected_transfer_2" },
        "ctop=true,cbottom=false,cnorth=true,csouth=false,ceast=false,cwest=false": { "model": "unimod:block/unicable_connected_transfer_2" },
        "ctop=true,cbottom=false,cnorth=false,csouth=true,ceast=false,cwest=false": { "model": "unimod:block/unicable_connected_transfer_2" },
        "ctop=true,cbottom=false,cnorth=false,csouth=false,ceast=true,cwest=false": { "model": "unimod:block/unicable_connected_transfer_2" },
        "ctop=true,cbottom=false,cnorth=false,csouth=false,ceast=false,cwest=true": { "model": "unimod:block/unicable_connected_transfer_2" },
        "ctop=false,cbottom=true,cnorth=true,csouth=false,ceast=false,cwest=false": { "model": "unimod:block/unicable_connected_transfer_2" },
        "ctop=false,cbottom=true,cnorth=false,csouth=true,ceast=false,cwest=false": { "model": "unimod:block/unicable_connected_transfer_2" },
        "ctop=false,cbottom=true,cnorth=false,csouth=false,ceast=true,cwest=false": { "model": "unimod:block/unicable_connected_transfer_2" },
        "ctop=false,cbottom=true,cnorth=false,csouth=false,ceast=false,cwest=true": { "model": "unimod:block/unicable_connected_transfer_2" },
        "ctop=false,cbottom=false,cnorth=true,csouth=true,ceast=false,cwest=false": { "model": "unimod:block/unicable_connected_transfer_2" },
        "ctop=false,cbottom=false,cnorth=true,csouth=false,ceast=true,cwest=false": { "model": "unimod:block/unicable_connected_transfer_2" },
        "ctop=false,cbottom=false,cnorth=true,csouth=false,ceast=false,cwest=true": { "model": "unimod:block/unicable_connected_transfer_2" },
        "ctop=false,cbottom=false,cnorth=false,csouth=true,ceast=true,cwest=false": { "model": "unimod:block/unicable_connected_transfer_2" },
        "ctop=false,cbottom=false,cnorth=false,csouth=true,ceast=false,cwest=true": { "model": "unimod:block/unicable_connected_transfer_2" },
        "ctop=false,cbottom=false,cnorth=false,csouth=false,ceast=true,cwest=true": { "model": "unimod:block/unicable_connected_transfer_2" },

        "ctop=true,cbottom=true,cnorth=true,csouth=false,ceast=false,cwest=false": { "model": "unimod:block/unicable_connected_transfer_3" },
        "ctop=true,cbottom=true,cnorth=false,csouth=true,ceast=false,cwest=false": { "model": "unimod:block/unicable_connected_transfer_3" },
        "ctop=true,cbottom=true,cnorth=false,csouth=false,ceast=true,cwest=false": { "model": "unimod:block/unicable_connected_transfer_3" },
        "ctop=true,cbottom=true,cnorth=false,csouth=false,ceast=false,cwest=true": { "model": "unimod:block/unicable_connected_transfer_3" },
        "ctop=true,cbottom=false,cnorth=true,csouth=true,ceast=false,cwest=false": { "model": "unimod:block/unicable_connected_transfer_3" },
        "ctop=true,cbottom=false,cnorth=true,csouth=false,ceast=true,cwest=false": { "model": "unimod:block/unicable_connected_transfer_3" },
        "ctop=true,cbottom=false,cnorth=true,csouth=false,ceast=false,cwest=true": { "model": "unimod:block/unicable_connected_transfer_3" },
        "ctop=true,cbottom=false,cnorth=false,csouth=true,ceast=true,cwest=false": { "model": "unimod:block/unicable_connected_transfer_3" },
        "ctop=true,cbottom=false,cnorth=false,csouth=false,ceast=true,cwest=true": { "model": "unimod:block/unicable_connected_transfer_3" },
        "ctop=false,cbottom=true,cnorth=true,csouth=true,ceast=false,cwest=false": { "model": "unimod:block/unicable_connected_transfer_3" },
        "ctop=false,cbottom=true,cnorth=true,csouth=false,ceast=true,cwest=false": { "model": "unimod:block/unicable_connected_transfer_3" },
        "ctop=false,cbottom=true,cnorth=true,csouth=false,ceast=false,cwest=true": { "model": "unimod:block/unicable_connected_transfer_3" },
        "ctop=false,cbottom=true,cnorth=false,csouth=true,ceast=true,cwest=false": { "model": "unimod:block/unicable_connected_transfer_3" },
        "ctop=false,cbottom=true,cnorth=false,csouth=true,ceast=false,cwest=true": { "model": "unimod:block/unicable_connected_transfer_3" },
        "ctop=false,cbottom=true,cnorth=false,csouth=false,ceast=true,cwest=true": { "model": "unimod:block/unicable_connected_transfer_3" },
        "ctop=false,cbottom=false,cnorth=true,csouth=true,ceast=true,cwest=false": { "model": "unimod:block/unicable_connected_transfer_3" },
        "ctop=false,cbottom=false,cnorth=true,csouth=true,ceast=false,cwest=true": { "model": "unimod:block/unicable_connected_transfer_3" },
        "ctop=false,cbottom=false,cnorth=true,csouth=false,ceast=true,cwest=true": { "model": "unimod:block/unicable_connected_transfer_3" },
        "ctop=false,cbottom=false,cnorth=false,csouth=true,ceast=true,cwest=true": { "model": "unimod:block/unicable_connected_transfer_3" },

        "ctop=true,cbottom=true,cnorth=true,csouth=true,ceast=false,cwest=false": { "model": "unimod:block/unicable_connected_transfer_4" },
        "ctop=true,cbottom=true,cnorth=true,csouth=false,ceast=true,cwest=false": { "model": "unimod:block/unicable_connected_transfer_4" },
        "ctop=true,cbottom=true,cnorth=true,csouth=false,ceast=false,cwest=true": { "model": "unimod:block/unicable_connected_transfer_4" },
        "ctop=true,cbottom=true,cnorth=false,csouth=true,ceast=true,cwest=false": { "model": "unimod:block/unicable_connected_transfer_4" },
        "ctop=true,cbottom=true,cnorth=false,csouth=true,ceast=false,cwest=true": { "model": "unimod:block/unicable_connected_transfer_4" },
        "ctop=true,cbottom=true,cnorth=false,csouth=false,ceast=true,cwest=true": { "model": "unimod:block/unicable_connected_transfer_4" },
        "ctop=true,cbottom=false,cnorth=true,csouth=true,ceast=true,cwest=false": { "model": "unimod:block/unicable_connected_transfer_4" },
        "ctop=true,cbottom=false,cnorth=true,csouth=true,ceast=false,cwest=true": { "model": "unimod:block/unicable_connected_transfer_4" },
        "ctop=true,cbottom=false,cnorth=true,csouth=false,ceast=true,cwest=true": { "model": "unimod:block/unicable_connected_transfer_4" },
        "ctop=true,cbottom=false,cnorth=false,csouth=true,ceast=true,cwest=true": { "model": "unimod:block/unicable_connected_transfer_4" },
        "ctop=false,cbottom=true,cnorth=true,csouth=true,ceast=true,cwest=false": { "model": "unimod:block/unicable_connected_transfer_4" },
        "ctop=false,cbottom=true,cnorth=true,csouth=true,ceast=false,cwest=true": { "model": "unimod:block/unicable_connected_transfer_4" },
        "ctop=false,cbottom=true,cnorth=true,csouth=false,ceast=true,cwest=true": { "model": "unimod:block/unicable_connected_transfer_4" },
        "ctop=false,cbottom=true,cnorth=false,csouth=true,ceast=true,cwest=true": { "model": "unimod:block/unicable_connected_transfer_4" },
        "ctop=false,cbottom=false,cnorth=true,csouth=true,ceast=true,cwest=true": { "model": "unimod:block/unicable_connected_transfer_4" },

        "ctop=true,cbottom=true,cnorth=true,csouth=true,ceast=true,cwest=false": { "model": "unimod:block/unicable_connected_transfer_5" },
        "ctop=true,cbottom=true,cnorth=true,csouth=true,ceast=false,cwest=true": { "model": "unimod:block/unicable_connected_transfer_5" },
        "ctop=true,cbottom=true,cnorth=true,csouth=false,ceast=true,cwest=true": { "model": "unimod:block/unicable_connected_transfer_5" },
        "ctop=true,cbottom=true,cnorth=false,csouth=true,ceast=true,cwest=true": { "model": "unimod:block/unicable_connected_transfer_5" },
        "ctop=true,cbottom=false,cnorth=true,csouth=true,ceast=true,cwest=true": { "model": "unimod:block/unicable_connected_transfer_5" },
        "ctop=false,cbottom=true,cnorth=true,csouth=true,ceast=true,cwest=true": { "model": "unimod:block/unicable_connected_transfer_5" },

        "ctop=true,cbottom=true,cnorth=true,csouth=true,ceast=true,cwest=true": { "model": "unimod:block/unicable_connected_transfer_6" }
    }
}